conga_office/__init__.py
conga_office/tools.py
conga_office/config/__init__.py
conga_office/config/metadata.py
conga_office-0.2.0.dist-info/LICENSE
conga_office-0.2.0.dist-info/METADATA
conga_office-0.2.0.dist-info/WHEEL
conga_office-0.2.0.dist-info/top_level.txt
conga_office-0.2.0.dist-info/RECORD
