Metadata-Version: 2.1
Name: conga-office
Version: 0.2.0
Summary: Python library thought to active conga-office in order to appear online to your employer while grabbing a coffee or having creativity sessions.
Home-page: https://github.com/mielgosez/conga_office
Author: Jose Mielgo
Author-email: mielgosez@gmail.com
License: UNKNOWN
Project-URL: Bug Tracker, https://github.com/mielgosez/conga_office/issues
Platform: UNKNOWN
Classifier: Programming Language :: Python :: 3
Classifier: License :: OSI Approved :: MIT License
Classifier: Operating System :: OS Independent
Requires-Python: >=3.6
License-File: LICENSE
Requires-Dist: pyautogui
Requires-Dist: requests
Requires-Dist: numpy
